console_logs/Logging.py
console_logs/src/utils.py
console_logs-1.0.2.dist-info/METADATA
console_logs-1.0.2.dist-info/WHEEL
console_logs-1.0.2.dist-info/top_level.txt
console_logs-1.0.2.dist-info/RECORD
