Metadata-Version: 2.1
Name: console-logs
Version: 1.0.2
Summary: Logging made easier
Author: xenny
Requires-Dist: requests
Requires-Dist: colorama
Requires-Dist: Crypto.Cipher
Requires-Dist: pycryptodome
